Metadata-Version: 2.1
Name: pyiocontrol
Version: 0.7.6
Summary: iocontrol.ru module for iocontorl.ru api
Home-page: http://github.com/tremaru/pyiocontrol
Author: iocontrol.ru
Author-email: info@iocontrol.ru
License: MIT
Platform: UNKNOWN
Classifier: Programming Language :: Python :: 3
